affiliate/__init__.py
affiliate/admin.py
affiliate/apps.py
affiliate/decorators.py
affiliate/manager.py
affiliate/models.py
affiliate/tests.py
affiliate/views.py
affiliate/migrations/0001_initial.py
affiliate/migrations/0002_auto_20210602_1238.py
affiliate/migrations/0003_auto_20210602_1245.py
affiliate/migrations/0004_auto_20210602_1246.py
affiliate/migrations/__init__.py
django_track_affiliate-0.0.2.dist-info/LICENSE
django_track_affiliate-0.0.2.dist-info/METADATA
django_track_affiliate-0.0.2.dist-info/WHEEL
django_track_affiliate-0.0.2.dist-info/top_level.txt
django_track_affiliate-0.0.2.dist-info/RECORD
