Metadata-Version: 2.1
Name: django-track-affiliate
Version: 0.0.2
Summary: A Django app to help manage and track affiliate programmes
Home-page: https://github.com/bobby-didcoding/django-track-affiliate
Author: Bobby Stearman
Author-email: bobby@didcoding.com
License: UNKNOWN
Project-URL: Bug Tracker, https://github.com/bobby-didcoding/django-track-affiliate/issues
Platform: UNKNOWN
Classifier: Programming Language :: Python :: 3
Classifier: License :: OSI Approved :: BSD License
Classifier: Operating System :: OS Independent
Requires-Python: >=3.6
License-File: LICENSE
Requires-Dist: Django (>=3.2)
